berxel_py_wrapper/__init__.py
berxel_py_wrapper/Python/__init__.py
berxel_py_wrapper/Python/BerxelSdkDriver/BerxelHawkContext.py
berxel_py_wrapper/Python/BerxelSdkDriver/BerxelHawkDefines.py
berxel_py_wrapper/Python/BerxelSdkDriver/BerxelHawkDevice.py
berxel_py_wrapper/Python/BerxelSdkDriver/BerxelHawkFrame.py
berxel_py_wrapper/Python/BerxelSdkDriver/BerxelHawkNativeMethods.py
berxel_py_wrapper/Python/BerxelSdkDriver/__init__.py
berxel_py_wrapper/Python/BerxelSdkDriver/libs/linux/arm64/libBerxelCommonDriver.so
berxel_py_wrapper/Python/BerxelSdkDriver/libs/linux/arm64/libBerxelHawk.so
berxel_py_wrapper/Python/BerxelSdkDriver/libs/linux/arm64/libBerxelInterface.so
berxel_py_wrapper/Python/BerxelSdkDriver/libs/linux/arm64/libBerxelLogDriver.so
berxel_py_wrapper/Python/BerxelSdkDriver/libs/linux/arm64/libBerxelNetDriver.so
berxel_py_wrapper/Python/BerxelSdkDriver/libs/linux/arm64/libBerxelUvcDriver.so
berxel_py_wrapper/Python/BerxelSdkDriver/libs/linux/arm64/params.bin
berxel_py_wrapper/Python/BerxelSdkDriver/libs/linux/arm64/params100E.bin
berxel_py_wrapper/Python/BerxelSdkDriver/libs/linux/arm64/params100Q.bin
berxel_py_wrapper/Python/BerxelSdkDriver/libs/linux/arm64/params137_0.bin
berxel_py_wrapper/Python/BerxelSdkDriver/libs/linux/arm64/params137_1.bin
berxel_py_wrapper/Python/BerxelSdkDriver/libs/linux/x86/berxelLog.ini
berxel_py_wrapper/Python/BerxelSdkDriver/libs/linux/x86/libBerxelCommonDriver.so
berxel_py_wrapper/Python/BerxelSdkDriver/libs/linux/x86/libBerxelHawk.so
berxel_py_wrapper/Python/BerxelSdkDriver/libs/linux/x86/libBerxelInterface.so
berxel_py_wrapper/Python/BerxelSdkDriver/libs/linux/x86/libBerxelLogDriver.so
berxel_py_wrapper/Python/BerxelSdkDriver/libs/linux/x86/libBerxelNetDriver.so
berxel_py_wrapper/Python/BerxelSdkDriver/libs/linux/x86/libBerxelUvcDriver.so
berxel_py_wrapper/Python/BerxelSdkDriver/libs/linux/x86/params.bin
berxel_py_wrapper/Python/BerxelSdkDriver/libs/linux/x86/params100E.bin
berxel_py_wrapper-2.0.189.dist-info/licenses/LICENSE
berxel_py_wrapper-2.0.189.dist-info/METADATA
berxel_py_wrapper-2.0.189.dist-info/WHEEL
berxel_py_wrapper-2.0.189.dist-info/top_level.txt
berxel_py_wrapper-2.0.189.dist-info/RECORD
